infra_event_notifier/__init__.py
infra_event_notifier/notifier.py
infra_event_notifier/backends/__init__.py
infra_event_notifier/backends/datadog.py
infra_event_notifier/backends/jira.py
infra_event_notifier/backends/slack.py
infra_event_notifier-0.0.1.dist-info/LICENSE
infra_event_notifier-0.0.1.dist-info/METADATA
infra_event_notifier-0.0.1.dist-info/WHEEL
infra_event_notifier-0.0.1.dist-info/top_level.txt
infra_event_notifier-0.0.1.dist-info/RECORD
