Metadata-Version: 2.1
Name: infra_event_notifier
Version: 0.0.1
Summary: Package to send notifications to various backends (datadog/slack/jira)
Project-URL: Homepage, https://github.com/getsentry/infra-event-notifier
Project-URL: Issues, https://github.com/getsentry/infra-event-notifier/issues
Requires-Python: >=311
License-File: LICENSE
